cloudsecgpt/.DS_Store
cloudsecgpt/__init__.py
cloudsecgpt/chat.py
cloudsecgpt/cli.py
cloudsecgpt/contexts/__init__.py
cloudsecgpt/contexts/json_asff.py
cloudsecgpt/contexts/json_ocsf.py
cloudsecgpt/core.py
cloudsecgpt/core_helpers.py
cloudsecgpt/models/__init__.py
cloudsecgpt/models/bedrock_model.py
cloudsecgpt/models/gemini_model.py
cloudsecgpt/models/mcp_model.py
cloudsecgpt/models/ollama_model.py
cloudsecgpt/models/openai_model.py
cloudsecgpt/protocols/__init__.py
cloudsecgpt/protocols/triage.py
cloudsecgpt/report.py
cloudsecgpt/templates/report.html.j2
cloudsecgpt/utils/__init__.py
cloudsecgpt/utils/cache.py
cloudsecgpt/utils/console.py
cloudsecgpt/utils/files.py
cloudsecgpt-0.1.1.dist-info/LICENSE
cloudsecgpt-0.1.1.dist-info/METADATA
cloudsecgpt-0.1.1.dist-info/WHEEL
cloudsecgpt-0.1.1.dist-info/entry_points.txt
cloudsecgpt-0.1.1.dist-info/RECORD
