Metadata-Version: 2.3
Name: cloudsecgpt
Version: 0.1.1
Summary: CloudSecGPT super-charges raw cloud-security findings with AI. Analyzes OCSF/Parquet exports and live data from AWS Security Hub, GCP Security Command Center, and Azure Defender to provide risk scores, summaries, remediation steps, alert clustering, and interactive chat capabilities.
License: Apache-2.0
Keywords: cloud security,ai,llm,gpt,openai,amazon bedrock,google gemini,ollama,mcp,aws security hub,gcp scc,azure defender,ocsf,asff,parquet,triage,risk score,remediation,devsecops,cli
Author: Sergio Garcia @MrCloudSec
Author-email: hello@mistercloudsec.com
Requires-Python: >=3.9
Classifier: License :: OSI Approved :: Apache Software License
Classifier: Programming Language :: Python :: 3
Classifier: Programming Language :: Python :: 3.9
Classifier: Programming Language :: Python :: 3.10
Classifier: Programming Language :: Python :: 3.11
Classifier: Programming Language :: Python :: 3.12
Classifier: Programming Language :: Python :: 3.13
Requires-Dist: azure-identity (==1.23.0)
Requires-Dist: azure-mgmt-resource (==24.0.0)
Requires-Dist: azure-mgmt-security (==7.0.0)
Requires-Dist: boto3 (==1.39.0)
Requires-Dist: google-cloud-resource-manager (==1.14.2)
Requires-Dist: google-cloud-securitycenter (==1.38.1)
Requires-Dist: google-generativeai (==0.8.3)
Requires-Dist: jinja2 (==3.1.6)
Requires-Dist: openai (==1.93.0)
Requires-Dist: pandas (==2.3.0)
Requires-Dist: requests (==2.32.4)
Requires-Dist: rich (==14.0.0)
Project-URL: homepage, https://github.com/MrCloudSec/CloudSecGPT
Project-URL: issues, https://github.com/MrCloudSec/CloudSecGPT/issues
